silos/__init__.py
silos/silos.py
silos-0.1.0.dist-info/AUTHORS.rst
silos-0.1.0.dist-info/LICENSE
silos-0.1.0.dist-info/METADATA
silos-0.1.0.dist-info/WHEEL
silos-0.1.0.dist-info/top_level.txt
silos-0.1.0.dist-info/RECORD
