Metadata-Version: 2.1
Name: silos
Version: 0.1.0
Summary: Easy Automation using Selenium
Home-page: https://github.com/umrashrf/silos
Author: Umair Ashraf
Author-email: umrashrf@gmail.com
License: GNU General Public License v3
Keywords: silos
Platform: UNKNOWN
Classifier: Development Status :: 2 - Pre-Alpha
Classifier: Intended Audience :: Developers
Classifier: License :: OSI Approved :: GNU General Public License v3 (GPLv3)
Classifier: Natural Language :: English
Classifier: Programming Language :: Python :: 2
Classifier: Programming Language :: Python :: 2.7
Classifier: Programming Language :: Python :: 3
Classifier: Programming Language :: Python :: 3.4
Classifier: Programming Language :: Python :: 3.5
Classifier: Programming Language :: Python :: 3.6
Classifier: Programming Language :: Python :: 3.7
